{
    "family": "sctp-cloud-infra_yuyuan",
    "executionRoleArn": "arn:aws:ecs:ap-southeast-1:255945442255:task/yuyuan-cluster/360f78635d2f4631a9b9c4e6395e8239",
    "networkMode": "awsvpc",
    "containerDefinitions": [
        {
            "name": "sctp-cloud-infra_yuyuan",
            "image": "255945442255.dkr.ecr.ap-southeast-1.amazonaws.com/yuyuan_3.5:latest", 
            "portMappings": [
                {
                    "containerPort": 8080,
                    "hostPort": 8080,
                    "protocol": "tcp"
                }
            ],
            "essential": true
        }
    ],
    "requiresCompatibilities": [
        "FARGATE"
    ],
    "cpu": "512",
    "memory": "1024"
}
